[{"muokkauspv_dr": ["08.01.2015 00:00:00", "05.02.2015 02:00:00"], "osm_ways": [{"osm_id": "189553072", "osm_timestamp": "2012-12-04T23:14:18Z", "name_sv_osm": "Slättvägen"}], "tienimi_ru": "Stationsbågen", "name": "Asemankaari"}, {"muokkauspv_dr": ["08.01.2015 00:00:00"], "osm_ways": [{"osm_id": "10723186", "osm_timestamp": "2016-04-28T16:28:39Z", "name_sv_osm": "Kallbergsvägen"}, {"osm_id": "414216628", "osm_timestamp": "2016-04-28T16:28:37Z", "name_sv_osm": "Kallbergsvägen"}], "tienimi_ru": "Kalbergsvägen", "name": "Avokalliontie"}, {"muokkauspv_dr": ["31.03.2016 22:55:03"], "osm_ways": [{"osm_id": "10614711", "osm_timestamp": "2016-03-02T09:49:19Z", "name_sv_osm": "Elfvingsgränd"}], "tienimi_ru": "Elfvingsgränden", "name": "Elfvinginkuja"}, {"muokkauspv_dr": ["08.01.2015 00:00:00", "29.09.2016 02:00:22", "31.07.2015 03:00:00", "03.03.2017 17:11:34"], "osm_ways": [{"osm_id": "29989056", "osm_timestamp": "2016-08-28T11:08:06Z", "name_sv_osm": "Evitskogvägen"}, {"osm_id": "29989071", "osm_timestamp": "2016-08-28T11:08:07Z", "name_sv_osm": "Evitskogvägen"}, {"osm_id": "29989072", "osm_timestamp": "2016-08-28T11:08:07Z", "name_sv_osm": "Evitskogvägen"}, {"osm_id": "29989074", "osm_timestamp": "2016-08-28T09:38:42Z", "name_sv_osm": "Evitskogvägen"}, {"osm_id": "29989077", "osm_timestamp": "2016-08-28T09:05:20Z", "name_sv_osm": "Evitskogvägen"}, {"osm_id": "70379154", "osm_timestamp": "2014-03-10T20:17:18Z", "name_sv_osm": "Evitskogvägen"}, {"osm_id": "70411418", "osm_timestamp": "2016-08-28T11:08:06Z", "name_sv_osm": "Evitskogvägen"}, {"osm_id": "70411421", "osm_timestamp": "2016-09-04T10:27:21Z", "name_sv_osm": "Evitskogvägen"}, {"osm_id": "70415897", "osm_timestamp": "2016-08-28T11:08:05Z", "name_sv_osm": "Evitskogvägen"}, {"osm_id": "239618727", "osm_timestamp": "2016-08-28T11:08:05Z", "name_sv_osm": "Evitskogvägen"}, {"osm_id": "239618728", "osm_timestamp": "2014-02-18T17:14:07Z", "name_sv_osm": "Evitskogvägen"}], "tienimi_ru": "Evitskogsvägen", "name": "Evitskogintie"}, {"muokkauspv_dr": ["29.09.2016 02:00:22", "26.09.2016 03:00:00", "08.01.2015 00:00:00"], "osm_ways": [{"osm_id": "265973943", "osm_timestamp": "2017-02-25T10:16:09Z", "name_sv_osm": "Aspnäsvägen"}], "tienimi_ru": "Haapaniemivägen", "name": "Haapaniementie"}, {"muokkauspv_dr": ["08.01.2015 00:00:00"], "osm_ways": [{"osm_id": "9475978", "osm_timestamp": "2011-11-08T12:52:00Z", "name_sv_osm": "Hoksvangen"}], "tienimi_ru": "Höksvängen", "name": "Haukankäyrä"}, {"muokkauspv_dr": ["08.01.2015 00:00:00"], "osm_ways": [{"osm_id": "67626755", "osm_timestamp": "2013-10-14T10:16:18Z", "name_sv_osm": "Hindersbyvägen"}], "tienimi_ru": "Hindersbytorg", "name": "Heikkiläntori"}, {"muokkauspv_dr": ["29.09.2016 02:00:22"], "osm_ways": [{"osm_id": "38899547", "osm_timestamp": "2017-02-26T10:23:06Z", "name_sv_osm": "Hendriksdalsvägen"}], "tienimi_ru": "Henriksdalsvägen", "name": "Henriksdalintie"}, {"muokkauspv_dr": ["13.10.2016 02:00:15"], "osm_ways": [{"osm_id": "31112614", "osm_timestamp": "2016-09-12T15:21:24Z", "name_sv_osm": "Henriksronsvägen"}], "tienimi_ru": "Henriksrovägen", "name": "Henriksrontie"}, {"muokkauspv_dr": ["29.09.2016 02:00:22"], "osm_ways": [{"osm_id": "16230356", "osm_timestamp": "2017-03-19T09:15:10Z", "name_sv_osm": "Hummelrödslandsvägen"}], "tienimi_ru": "Hummelrödslansvägen", "name": "Hummelrödslanintie"}, {"muokkauspv_dr": ["29.09.2016 02:00:22", "08.01.2015 00:00:00"], "osm_ways": [{"osm_id": "39297532", "osm_timestamp": "2017-02-19T09:52:48Z", "name_sv_osm": "Storaängsvägen"}], "tienimi_ru": "Storängsvägen", "name": "Isonniityntie"}, {"muokkauspv_dr": ["08.01.2015 00:00:00"], "osm_ways": [{"osm_id": "9476627", "osm_timestamp": "2012-10-03T22:37:39Z", "name_sv_osm": "Brunnsgränden"}], "tienimi_ru": "Brunngränden", "name": "Kaivokuja"}, {"muokkauspv_dr": ["31.03.2016 22:55:03", "08.01.2015 00:00:00"], "osm_ways": [{"osm_id": "23021649", "osm_timestamp": "2008-02-18T21:33:05Z", "name_sv_osm": "Jungbackavägen"}], "tienimi_ru": "Ljungbackavägen", "name": "Kanervamäentie"}, {"muokkauspv_dr": ["08.01.2015 00:00:00"], "osm_ways": [{"osm_id": "185398207", "osm_timestamp": "2013-02-26T08:31:45Z", "name_sv_osm": "Björniden"}], "tienimi_ru": "Björnidet", "name": "Karhunpesä"}, {"muokkauspv_dr": ["08.01.2015 00:00:00"], "osm_ways": [{"osm_id": "443600028", "osm_timestamp": "2016-09-21T13:29:09Z", "name_sv_osm": "Konsulsgränden"}], "tienimi_ru": "Konsulns gränd", "name": "Konsulinkuja"}, {"muokkauspv_dr": ["08.01.2015 00:00:00"], "osm_ways": [{"osm_id": "443599856", "osm_timestamp": "2016-09-21T13:29:10Z", "name_sv_osm": "Konsulsbriken"}], "tienimi_ru": "Konsulns brink", "name": "Konsulinrinne"}, {"muokkauspv_dr": ["08.01.2015 00:00:00", "13.10.2016 02:00:15", "31.03.2016 22:55:03"], "osm_ways": [{"osm_id": "38585805", "osm_timestamp": "2016-09-12T15:08:29Z", "name_sv_osm": "Hemgräden"}], "tienimi_ru": "Hemgränden", "name": "Kotikuja"}, {"muokkauspv_dr": ["08.01.2015 00:00:00", "30.09.2016 02:00:12"], "osm_ways": [{"osm_id": "443600164", "osm_timestamp": "2016-09-21T13:36:25Z", "name_sv_osm": "Lagemannssvängen"}], "tienimi_ru": "Lagemannsvägen", "name": "Laamanninkaari"}, {"muokkauspv_dr": ["08.01.2015 00:00:00", "31.03.2016 22:55:03"], "osm_ways": [{"osm_id": "10674426", "osm_timestamp": "2015-03-14T08:32:48Z", "name_sv_osm": "Lindalvägen"}, {"osm_id": "194445112", "osm_timestamp": "2012-12-04T10:09:32Z", "name_sv_osm": "Lindalvägen"}, {"osm_id": "194445147", "osm_timestamp": "2012-12-04T10:09:35Z", "name_sv_osm": "Lindalvägen"}, {"osm_id": "194445156", "osm_timestamp": "2015-03-14T08:32:52Z", "name_sv_osm": "Lindalvägen"}], "tienimi_ru": "Lindalsvägen", "name": "Lindalintie"}, {"muokkauspv_dr": ["08.01.2015 00:00:00"], "osm_ways": [{"osm_id": "5001807", "osm_timestamp": "2012-12-04T10:09:39Z", "name_sv_osm": "Klockargränd"}], "tienimi_ru": "Klockargränden", "name": "Lukkarinkuja"}, {"muokkauspv_dr": ["08.01.2015 00:00:00", "29.09.2016 02:00:22"], "osm_ways": [{"osm_id": "34634694", "osm_timestamp": "2013-03-22T14:08:08Z", "name_sv_osm": "Bobäcksstanden"}], "tienimi_ru": "Bobäckstranden", "name": "Luomanranta"}, {"muokkauspv_dr": ["14.10.2016 09:33:35", "13.10.2016 02:00:15", "14.10.2016 09:33:37"], "osm_ways": [{"osm_id": "4976986", "osm_timestamp": "2012-11-16T06:50:07Z", "name_sv_osm": "Makasinvägen"}], "tienimi_ru": "Magasinvägen", "name": "Makasiinitie"}, {"muokkauspv_dr": ["31.07.2015 03:00:00", "29.09.2016 02:00:22"], "osm_ways": [{"osm_id": "64979449", "osm_timestamp": "2017-03-25T10:23:04Z", "name_sv_osm": "Mariefredvägen"}], "tienimi_ru": "Mariefredsvägen", "name": "Mariefredintie"}, {"muokkauspv_dr": ["08.01.2015 00:00:00"], "osm_ways": [{"osm_id": "137825998", "osm_timestamp": "2017-02-05T20:13:45Z", "name_sv_osm": "Mathindebergvägen"}], "tienimi_ru": "Mathildebergsvägen", "name": "Mathildebergintie"}, {"muokkauspv_dr": ["03.12.2015 01:28:54"], "osm_ways": [{"osm_id": "35801135", "osm_timestamp": "2017-03-19T08:49:01Z", "name_sv_osm": "Skogsträskvägen"}], "tienimi_ru": "Skogsträsksvägen", "name": "Metsälammentie"}, {"muokkauspv_dr": ["08.01.2015 00:00:00", "31.03.2016 22:55:03", "06.04.2016 12:50:06", "26.03.2016 02:00:00"], "osm_ways": [{"osm_id": "26216742", "osm_timestamp": "2017-03-19T09:52:00Z", "name_sv_osm": "Morsfjärdvägen"}, {"osm_id": "27148255", "osm_timestamp": "2009-08-13T19:06:28Z", "name_sv_osm": "Morsfjärdvägen"}, {"osm_id": "27148256", "osm_timestamp": "2008-09-18T09:34:14Z", "name_sv_osm": "Morsfjärdvägen"}], "tienimi_ru": "Morsfjärdsvägen", "name": "Morsfjärdintie"}, {"muokkauspv_dr": ["29.09.2016 02:00:22"], "osm_ways": [{"osm_id": "37732124", "osm_timestamp": "2017-02-11T09:47:06Z", "name_sv_osm": "Kvarnåkernsvägen"}], "tienimi_ru": "Kvarnåkersvägen", "name": "Myllypellontie"}, {"muokkauspv_dr": ["31.03.2016 22:55:03"], "osm_ways": [{"osm_id": "23021371", "osm_timestamp": "2012-12-02T10:08:14Z", "name_sv_osm": "Ragövägen"}], "tienimi_ru": "Rågövägen", "name": "Pakrintie"}, {"muokkauspv_dr": ["29.09.2016 02:00:22", "26.09.2016 03:00:00"], "osm_ways": [{"osm_id": "44953172", "osm_timestamp": "2017-02-19T09:52:48Z", "name_sv_osm": "Petäjärvivågen"}], "tienimi_ru": "Petäjärvivägen", "name": "Petäjärventie"}, {"muokkauspv_dr": ["08.01.2015 00:00:00"], "osm_ways": [{"osm_id": "11079255", "osm_timestamp": "2007-11-05T11:46:31Z", "name_sv_osm": "Norrabacken"}, {"osm_id": "11079257", "osm_timestamp": "2007-11-05T11:46:31Z", "name_sv_osm": "Norrabacken"}], "tienimi_ru": "Norrbacken", "name": "Pohjoispiha"}, {"muokkauspv_dr": ["08.01.2015 00:00:00"], "osm_ways": [{"osm_id": "10384239", "osm_timestamp": "2013-10-19T20:22:22Z", "name_sv_osm": "Skräddar Bäckströms gränd"}], "tienimi_ru": "Skäddar Bäckströms gränd", "name": "Räätäli Bäckströmin kuja"}, {"muokkauspv_dr": ["08.01.2015 00:00:00"], "osm_ways": [{"osm_id": "5001782", "osm_timestamp": "2007-08-01T04:45:31Z", "name_sv_osm": "Ravalstigen"}], "tienimi_ru": "Ravalsstigen", "name": "Ravalsinpolku"}, {"muokkauspv_dr": ["31.03.2016 22:55:03", "05.11.2015 14:48:01"], "osm_ways": [{"osm_id": "370852438", "osm_timestamp": "2015-09-16T10:01:30Z", "name_sv_osm": "Ruhlasvägen"}], "tienimi_ru": "Ruhlavägen", "name": "Ruhlantie"}, {"muokkauspv_dr": ["31.03.2016 22:55:03"], "osm_ways": [{"osm_id": "5035179", "osm_timestamp": "2007-08-07T00:33:26Z", "name_sv_osm": "Sandalsgränden"}], "tienimi_ru": "Sandalgränden", "name": "Sandalinkuja"}, {"muokkauspv_dr": ["26.03.2016 02:00:00", "31.03.2016 22:55:03"], "osm_ways": [{"osm_id": "146991120", "osm_timestamp": "2015-09-21T11:24:09Z", "name_sv_osm": "Sarvvikspår"}], "tienimi_ru": "Sarvviksstigen", "name": "Sarvvikinpolku"}, {"muokkauspv_dr": ["13.10.2016 02:00:15"], "osm_ways": [{"osm_id": "180382084", "osm_timestamp": "2016-04-22T10:39:39Z", "name_sv_osm": "Sarvviksbrinken"}], "tienimi_ru": "Sarvviksslänten", "name": "Sarvvikinrinne"}, {"muokkauspv_dr": ["08.01.2015 00:00:00"], "osm_ways": [{"osm_id": "10724708", "osm_timestamp": "2007-11-02T02:56:30Z", "name_sv_osm": "Smedsstigen"}], "tienimi_ru": "Smedstigen", "name": "Sepänpolku"}, {"muokkauspv_dr": ["08.01.2015 00:00:00"], "osm_ways": [{"osm_id": "443933161", "osm_timestamp": "2017-03-21T20:13:21Z", "name_sv_osm": "Brostranden"}], "tienimi_ru": "Brostrandsgränden", "name": "Siltarannankuja"}, {"muokkauspv_dr": ["31.03.2016 22:55:03"], "osm_ways": [{"osm_id": "8393651", "osm_timestamp": "2016-09-29T07:07:45Z", "name_sv_osm": "Skognymfsvägen"}, {"osm_id": "137051457", "osm_timestamp": "2016-09-29T07:07:45Z", "name_sv_osm": "Skognymfsvägen"}], "tienimi_ru": "Skogsnymfsvägen", "name": "Sinipiiantie"}, {"muokkauspv_dr": ["31.03.2016 22:55:03", "08.01.2015 00:00:00", "29.07.2015 14:32:57"], "osm_ways": [{"osm_id": "4339750", "osm_timestamp": "2016-09-21T13:27:45Z", "name_sv_osm": "Sundets Àlle"}, {"osm_id": "85816642", "osm_timestamp": "2016-09-22T09:16:52Z", "name_sv_osm": "Sundets Àlle"}, {"osm_id": "85816643", "osm_timestamp": "2016-09-22T09:13:25Z", "name_sv_osm": "Sundets Àlle"}], "tienimi_ru": "Sundets allé", "name": "Sundetin puistotie"}, {"muokkauspv_dr": ["08.01.2015 00:00:00"], "osm_ways": [{"osm_id": "41873538", "osm_timestamp": "2016-08-28T09:05:32Z", "name_sv_osm": "Tjämen"}], "tienimi_ru": "Tjärnen", "name": "Suolampi"}, {"muokkauspv_dr": ["01.04.2016 01:15:30", "01.04.2016 01:15:07", "01.04.2016 01:15:27"], "osm_ways": [{"osm_id": "443597445", "osm_timestamp": "2016-09-21T13:03:49Z", "name_sv_osm": "Stormhattsstigen"}], "tienimi_ru": "Stormhatsstigen", "name": "Ukonhatunpolku"}, {"muokkauspv_dr": ["14.04.2016 16:16:15"], "osm_ways": [{"osm_id": "4339427", "osm_timestamp": "2014-05-31T20:38:40Z", "name_sv_osm": "Åskkviggsvägen"}], "tienimi_ru": "Åskviggsvägen", "name": "Ukonvaajantie"}, {"muokkauspv_dr": ["08.01.2015 00:00:00"], "osm_ways": [{"osm_id": "10383729", "osm_timestamp": "2017-03-19T13:10:53Z", "name_sv_osm": "Gamla Sjukhusvägen"}], "tienimi_ru": "Gamla sjukhusvägen", "name": "Vanha sairaalantie"}, {"muokkauspv_dr": ["08.01.2015 00:00:00", "27.09.2016 03:00:00", "30.09.2016 02:00:12"], "osm_ways": [{"osm_id": "443600892", "osm_timestamp": "2016-09-21T13:41:03Z", "name_sv_osm": "paved"}], "tienimi_ru": "Friherrsstig", "name": "Vapaaherranpolku"}, {"muokkauspv_dr": ["08.01.2015 00:00:00"], "osm_ways": [{"osm_id": "443599460", "osm_timestamp": "2016-09-22T09:16:53Z", "name_sv_osm": "Friherrsvägen"}], "tienimi_ru": "Friherrnsväg", "name": "Vapaaherrantie"}]